{
  "recenttracks": {
    "track": [
      {
        "artist": {
          "mbid": "9e0e2b01-41db-4008-bd8b-988977d6019a",
          "#text": "The Police"
        },
        "streamable": "0",
        "image": [
          {
            "size": "small",
            "#text": "https://lastfm.freetls.fastly.net/i/u/34s/e67e3d129294f6566907566bd24a97d8.png"
          },
          {
            "size": "medium",
            "#text": "https://lastfm.freetls.fastly.net/i/u/64s/e67e3d129294f6566907566bd24a97d8.png"
          },
          {
            "size": "large",
            "#text": "https://lastfm.freetls.fastly.net/i/u/174s/e67e3d129294f6566907566bd24a97d8.png"
          },
          {
            "size": "extralarge",
            "#text": "https://lastfm.freetls.fastly.net/i/u/300x300/e67e3d129294f6566907566bd24a97d8.png"
          }
        ],
        "mbid": "",
        "album": {
          "mbid": "069eb645-f2b3-4277-96a7-d32eb7d8db9c",
          "#text": "The Police"
        },
        "name": "Every Breath You Take",
        "url": "https://www.last.fm/music/The+Police/_/Every+Breath+You+Take",
        "date": {
          "uts": "1750250185",
          "#text": "18 Jun 2025, 12:36"
        }
      },
      {
        "artist": {
          "mbid": "c8b03190-306c-4120-bb0b-6f2ebfc06ea9",
          "#text": "The Weeknd"
        },
        "streamable": "0",
        "image": [
          {
            "size": "small",
            "#text": "https://lastfm.freetls.fastly.net/i/u/34s/08e3f15aca0423b084fb49f342756f3b.png"
          },
          {
            "size": "medium",
            "#text": "https://lastfm.freetls.fastly.net/i/u/64s/08e3f15aca0423b084fb49f342756f3b.png"
          },
          {
            "size": "large",
            "#text": "https://lastfm.freetls.fastly.net/i/u/174s/08e3f15aca0423b084fb49f342756f3b.png"
          },
          {
            "size": "extralarge",
            "#text": "https://lastfm.freetls.fastly.net/i/u/300x300/08e3f15aca0423b084fb49f342756f3b.png"
          }
        ],
        "mbid": "",
        "album": {
          "mbid": "08791ceb-9f2a-4f48-9fb7-9eab2df6fc6e",
          "#text": "Starboy"
        },
        "name": "I Feel It Coming (feat. Daft Punk)",
        "url": "https://www.last.fm/music/The+Weeknd/_/I+Feel+It+Coming+(feat.+Daft+Punk)",
        "date": {
          "uts": "1750249921",
          "#text": "18 Jun 2025, 12:32"
        }
      },
      {
        "artist": {
          "mbid": "62b914a7-d775-4bb4-bb5e-d46e7df115b5",
          "#text": "Benson Boone"
        },
        "streamable": "0",
        "image": [
          {
            "size": "small",
            "#text": "https://lastfm.freetls.fastly.net/i/u/34s/be4a9ca7acbc732df8f044d66b443f09.jpg"
          },
          {
            "size": "medium",
            "#text": "https://lastfm.freetls.fastly.net/i/u/64s/be4a9ca7acbc732df8f044d66b443f09.jpg"
          },
          {
            "size": "large",
            "#text": "https://lastfm.freetls.fastly.net/i/u/174s/be4a9ca7acbc732df8f044d66b443f09.jpg"
          },
          {
            "size": "extralarge",
            "#text": "https://lastfm.freetls.fastly.net/i/u/300x300/be4a9ca7acbc732df8f044d66b443f09.jpg"
          }
        ],
        "mbid": "89b32742-aaa7-4289-a735-9f113ebf9e30",
        "album": {
          "mbid": "",
          "#text": "Walk Me Home..."
        },
        "name": "NIGHTS LIKE THESE",
        "url": "https://www.last.fm/music/Benson+Boone/_/NIGHTS+LIKE+THESE",
        "date": {
          "uts": "1750249698",
          "#text": "18 Jun 2025, 12:28"
        }
      },
      {
        "artist": {
          "mbid": "2fa0d3ac-b64c-401a-b0a1-4915ba6cc157",
          "#text": "Hoobastank"
        },
        "streamable": "0",
        "image": [
          {
            "size": "small",
            "#text": "https://lastfm.freetls.fastly.net/i/u/34s/a611f617897daf14cc8681f7bdc6182f.png"
          },
          {
            "size": "medium",
            "#text": "https://lastfm.freetls.fastly.net/i/u/64s/a611f617897daf14cc8681f7bdc6182f.png"
          },
          {
            "size": "large",
            "#text": "https://lastfm.freetls.fastly.net/i/u/174s/a611f617897daf14cc8681f7bdc6182f.png"
          },
          {
            "size": "extralarge",
            "#text": "https://lastfm.freetls.fastly.net/i/u/300x300/a611f617897daf14cc8681f7bdc6182f.png"
          }
        ],
        "mbid": "",
        "album": {
          "mbid": "",
          "#text": "The Reason - Single"
        },
        "name": "The Reason",
        "url": "https://www.last.fm/music/Hoobastank/_/The+Reason",
        "date": {
          "uts": "1750249490",
          "#text": "18 Jun 2025, 12:24"
        }
      }
    ],
    "@attr": {
      "user": "injoon5",
      "totalPages": "140",
      "page": "1",
      "perPage": "50",
      "total": "6989"
    }
  }
}