{
  "recenttracks": {
    "track": [
      {
        "artist": {
          "mbid": "0ab49580-c84f-44d4-875f-d83760ea2cfe",
          "#text": "Maroon 5"
        },
        "streamable": "0",
        "image": [
          {
            "size": "small",
            "#text": "https://lastfm.freetls.fastly.net/i/u/34s/bbf019744c23450f80c16a492c6917e0.png"
          },
          {
            "size": "medium",
            "#text": "https://lastfm.freetls.fastly.net/i/u/64s/bbf019744c23450f80c16a492c6917e0.png"
          },
          {
            "size": "large",
            "#text": "https://lastfm.freetls.fastly.net/i/u/174s/bbf019744c23450f80c16a492c6917e0.png"
          },
          {
            "size": "extralarge",
            "#text": "https://lastfm.freetls.fastly.net/i/u/300x300/bbf019744c23450f80c16a492c6917e0.png"
          }
        ],
        "mbid": "",
        "album": {
          "mbid": "00e79a61-3afe-4e52-a9c2-10b8c634fb12",
          "#text": "Songs About Jane"
        },
        "name": "She Will Be Loved",
        "@attr": {
          "nowplaying": "true"
        },
        "url": "https://www.last.fm/music/Maroon+5/_/She+Will+Be+Loved"
      },
      {
        "artist": {
          "mbid": "7eb1ce54-a355-41f9-8d68-e018b096d427",
          "#text": "Harry Styles"
        },
        "streamable": "0",
        "image": [
          {
            "size": "small",
            "#text": "https://lastfm.freetls.fastly.net/i/u/34s/931b66df2652b311fb1078ac189a2e96.jpg"
          },
          {
            "size": "medium",
            "#text": "https://lastfm.freetls.fastly.net/i/u/64s/931b66df2652b311fb1078ac189a2e96.jpg"
          },
          {
            "size": "large",
            "#text": "https://lastfm.freetls.fastly.net/i/u/174s/931b66df2652b311fb1078ac189a2e96.jpg"
          },
          {
            "size": "extralarge",
            "#text": "https://lastfm.freetls.fastly.net/i/u/300x300/931b66df2652b311fb1078ac189a2e96.jpg"
          }
        ],
        "mbid": "07bb7cd7-fd7a-4106-bff5-28eb150d1a3d",
        "album": {
          "mbid": "6d8f2455-baa3-423c-8607-b7ea4a560fe3",
          "#text": "Harry's House"
        },
        "name": "Daylight",
        "url": "https://www.last.fm/music/Harry+Styles/_/Daylight",
        "date": {
          "uts": "1742662290",
          "#text": "22 Mar 2025, 16:51"
        }
      },
      {
        "artist": {
          "mbid": "994fd4c8-a7d0-4a08-9f3a-7ad22aadd437",
          "#text": "Joan"
        },
        "streamable": "0",
        "image": [
          {
            "size": "small",
            "#text": "https://lastfm.freetls.fastly.net/i/u/34s/7fa94b781d9452ab91a7ee9872951d17.jpg"
          },
          {
            "size": "medium",
            "#text": "https://lastfm.freetls.fastly.net/i/u/64s/7fa94b781d9452ab91a7ee9872951d17.jpg"
          },
          {
            "size": "large",
            "#text": "https://lastfm.freetls.fastly.net/i/u/174s/7fa94b781d9452ab91a7ee9872951d17.jpg"
          },
          {
            "size": "extralarge",
            "#text": "https://lastfm.freetls.fastly.net/i/u/300x300/7fa94b781d9452ab91a7ee9872951d17.jpg"
          }
        ],
        "mbid": "28add9a3-d242-4886-a1de-70457b7d67b5",
        "album": {
          "mbid": "",
          "#text": "something special (hi) - Single"
        },
        "name": "something special",
        "url": "https://www.last.fm/music/Joan/_/something+special",
        "date": {
          "uts": "1742662129",
          "#text": "22 Mar 2025, 16:48"
        }
      },
      {
        "artist": {
          "mbid": "f4abc0b5-3f7a-4eff-8f78-ac078dbce533",
          "#text": "Billie Eilish"
        },
        "streamable": "0",
        "image": [
          {
            "size": "small",
            "#text": "https://lastfm.freetls.fastly.net/i/u/34s/e69971625c379772fb79213dccfa194f.jpg"
          },
          {
            "size": "medium",
            "#text": "https://lastfm.freetls.fastly.net/i/u/64s/e69971625c379772fb79213dccfa194f.jpg"
          },
          {
            "size": "large",
            "#text": "https://lastfm.freetls.fastly.net/i/u/174s/e69971625c379772fb79213dccfa194f.jpg"
          },
          {
            "size": "extralarge",
            "#text": "https://lastfm.freetls.fastly.net/i/u/300x300/e69971625c379772fb79213dccfa194f.jpg"
          }
        ],
        "mbid": "3a7e1970-069c-4761-a6b2-9046e54406bc",
        "album": {
          "mbid": "43869ac5-c515-41a4-8ce1-d4a0c67e30c1",
          "#text": "HIT ME HARD AND SOFT"
        },
        "name": "BIRDS OF A FEATHER",
        "url": "https://www.last.fm/music/Billie+Eilish/_/BIRDS+OF+A+FEATHER",
        "date": {
          "uts": "1742661945",
          "#text": "22 Mar 2025, 16:45"
        }
      }
    ],
    "@attr": {
      "user": "injoon5",
      "totalPages": "137",
      "page": "1",
      "perPage": "50",
      "total": "6836"
    }
  }
}