{
  "recenttracks": {
    "track": [
      {
        "artist": {
          "mbid": "8264722b-df00-467a-858e-5c97cda169c9",
          "#text": "Joji"
        },
        "streamable": "0",
        "image": [
          {
            "size": "small",
            "#text": "https://lastfm.freetls.fastly.net/i/u/34s/6f2784172913db6982b2f6de18b837f6.jpg"
          },
          {
            "size": "medium",
            "#text": "https://lastfm.freetls.fastly.net/i/u/64s/6f2784172913db6982b2f6de18b837f6.jpg"
          },
          {
            "size": "large",
            "#text": "https://lastfm.freetls.fastly.net/i/u/174s/6f2784172913db6982b2f6de18b837f6.jpg"
          },
          {
            "size": "extralarge",
            "#text": "https://lastfm.freetls.fastly.net/i/u/300x300/6f2784172913db6982b2f6de18b837f6.jpg"
          }
        ],
        "mbid": "",
        "album": {
          "mbid": "e26e8cbc-db4c-422a-a171-f0080a142c88",
          "#text": "SMITHEREENS"
        },
        "name": "Die for You",
        "@attr": {
          "nowplaying": "true"
        },
        "url": "https://www.last.fm/music/Joji/_/Die+for+You"
      },
      {
        "artist": {
          "mbid": "8264722b-df00-467a-858e-5c97cda169c9",
          "#text": "Joji"
        },
        "streamable": "0",
        "image": [
          {
            "size": "small",
            "#text": "https://lastfm.freetls.fastly.net/i/u/34s/6f2784172913db6982b2f6de18b837f6.jpg"
          },
          {
            "size": "medium",
            "#text": "https://lastfm.freetls.fastly.net/i/u/64s/6f2784172913db6982b2f6de18b837f6.jpg"
          },
          {
            "size": "large",
            "#text": "https://lastfm.freetls.fastly.net/i/u/174s/6f2784172913db6982b2f6de18b837f6.jpg"
          },
          {
            "size": "extralarge",
            "#text": "https://lastfm.freetls.fastly.net/i/u/300x300/6f2784172913db6982b2f6de18b837f6.jpg"
          }
        ],
        "mbid": "",
        "album": {
          "mbid": "e26e8cbc-db4c-422a-a171-f0080a142c88",
          "#text": "SMITHEREENS"
        },
        "name": "Die for You",
        "url": "https://www.last.fm/music/Joji/_/Die+for+You",
        "date": {
          "uts": "1730003491",
          "#text": "27 Oct 2024, 04:31"
        }
      },
      {
        "artist": {
          "mbid": "13174e45-ad9e-4ccf-83ef-19f69dc49136",
          "#text": "Franck Amsallem"
        },
        "streamable": "0",
        "image": [
          {
            "size": "small",
            "#text": "https://lastfm.freetls.fastly.net/i/u/34s/8255f13732e7b66dcf601c783c616bd3.jpg"
          },
          {
            "size": "medium",
            "#text": "https://lastfm.freetls.fastly.net/i/u/64s/8255f13732e7b66dcf601c783c616bd3.jpg"
          },
          {
            "size": "large",
            "#text": "https://lastfm.freetls.fastly.net/i/u/174s/8255f13732e7b66dcf601c783c616bd3.jpg"
          },
          {
            "size": "extralarge",
            "#text": "https://lastfm.freetls.fastly.net/i/u/300x300/8255f13732e7b66dcf601c783c616bd3.jpg"
          }
        ],
        "mbid": "",
        "album": {
          "mbid": "",
          "#text": "Summer Times (feat. Johannes Weidenmuller & Joe Chambers)"
        },
        "name": "You're My Everything (feat. Johannes Weidenmuller & Joe Chambers)",
        "url": "https://www.last.fm/music/Franck+Amsallem/_/You%27re+My+Everything+(feat.+Johannes+Weidenmuller+&+Joe+Chambers)",
        "date": {
          "uts": "1730003155",
          "#text": "27 Oct 2024, 04:25"
        }
      },
      {
        "artist": {
          "mbid": "c0ef2ba5-a7b7-40ea-bd27-30acccfcac11",
          "#text": "Lauv"
        },
        "streamable": "0",
        "image": [
          {
            "size": "small",
            "#text": "https://lastfm.freetls.fastly.net/i/u/34s/c79c6c7bc829683f297bfa915e24dc48.jpg"
          },
          {
            "size": "medium",
            "#text": "https://lastfm.freetls.fastly.net/i/u/64s/c79c6c7bc829683f297bfa915e24dc48.jpg"
          },
          {
            "size": "large",
            "#text": "https://lastfm.freetls.fastly.net/i/u/174s/c79c6c7bc829683f297bfa915e24dc48.jpg"
          },
          {
            "size": "extralarge",
            "#text": "https://lastfm.freetls.fastly.net/i/u/300x300/c79c6c7bc829683f297bfa915e24dc48.jpg"
          }
        ],
        "mbid": "beaff8be-003d-4e41-a83a-1f0a7cb41c34",
        "album": {
          "mbid": "",
          "#text": "2021 - Single"
        },
        "name": "2021",
        "url": "https://www.last.fm/music/Lauv/_/2021",
        "date": {
          "uts": "1730002827",
          "#text": "27 Oct 2024, 04:20"
        }
      }
    ],
    "@attr": {
      "user": "injoon5",
      "totalPages": "114",
      "page": "1",
      "perPage": "50",
      "total": "5691"
    }
  }
}