{
  "recenttracks": {
    "track": [
      {
        "artist": {
          "mbid": "",
          "#text": "Lady Gaga & Bruno Mars"
        },
        "streamable": "0",
        "image": [
          {
            "size": "small",
            "#text": "https://lastfm.freetls.fastly.net/i/u/34s/a57e0d24346039cab5ff184786ff122d.jpg"
          },
          {
            "size": "medium",
            "#text": "https://lastfm.freetls.fastly.net/i/u/64s/a57e0d24346039cab5ff184786ff122d.jpg"
          },
          {
            "size": "large",
            "#text": "https://lastfm.freetls.fastly.net/i/u/174s/a57e0d24346039cab5ff184786ff122d.jpg"
          },
          {
            "size": "extralarge",
            "#text": "https://lastfm.freetls.fastly.net/i/u/300x300/a57e0d24346039cab5ff184786ff122d.jpg"
          }
        ],
        "mbid": "098ed81a-fa33-4212-ac6d-2cc19dde5fef",
        "album": {
          "mbid": "",
          "#text": "Die with a Smile - Single"
        },
        "name": "Die with a Smile",
        "@attr": {
          "nowplaying": "true"
        },
        "url": "https://www.last.fm/music/Lady+Gaga+&+Bruno+Mars/_/Die+with+a+Smile"
      },
      {
        "artist": {
          "mbid": "",
          "#text": "Lady Gaga & Bruno Mars"
        },
        "streamable": "0",
        "image": [
          {
            "size": "small",
            "#text": "https://lastfm.freetls.fastly.net/i/u/34s/a57e0d24346039cab5ff184786ff122d.jpg"
          },
          {
            "size": "medium",
            "#text": "https://lastfm.freetls.fastly.net/i/u/64s/a57e0d24346039cab5ff184786ff122d.jpg"
          },
          {
            "size": "large",
            "#text": "https://lastfm.freetls.fastly.net/i/u/174s/a57e0d24346039cab5ff184786ff122d.jpg"
          },
          {
            "size": "extralarge",
            "#text": "https://lastfm.freetls.fastly.net/i/u/300x300/a57e0d24346039cab5ff184786ff122d.jpg"
          }
        ],
        "mbid": "098ed81a-fa33-4212-ac6d-2cc19dde5fef",
        "album": {
          "mbid": "",
          "#text": "Die with a Smile - Single"
        },
        "name": "Die with a Smile",
        "url": "https://www.last.fm/music/Lady+Gaga+&+Bruno+Mars/_/Die+with+a+Smile",
        "date": {
          "uts": "1742055556",
          "#text": "15 Mar 2025, 16:19"
        }
      },
      {
        "artist": {
          "mbid": "28aee606-d7a9-4b8d-b234-dd5e0d99c259",
          "#text": "Rixton"
        },
        "streamable": "0",
        "image": [
          {
            "size": "small",
            "#text": "https://lastfm.freetls.fastly.net/i/u/34s/a2a28b1458c5fb630d614ac058517f3c.png"
          },
          {
            "size": "medium",
            "#text": "https://lastfm.freetls.fastly.net/i/u/64s/a2a28b1458c5fb630d614ac058517f3c.png"
          },
          {
            "size": "large",
            "#text": "https://lastfm.freetls.fastly.net/i/u/174s/a2a28b1458c5fb630d614ac058517f3c.png"
          },
          {
            "size": "extralarge",
            "#text": "https://lastfm.freetls.fastly.net/i/u/300x300/a2a28b1458c5fb630d614ac058517f3c.png"
          }
        ],
        "mbid": "",
        "album": {
          "mbid": "44ef15ac-603e-465d-b4c1-a16c565cb1d1",
          "#text": "Let the Road"
        },
        "name": "Me and My Broken Heart",
        "url": "https://www.last.fm/music/Rixton/_/Me+and+My+Broken+Heart",
        "date": {
          "uts": "1742055359",
          "#text": "15 Mar 2025, 16:15"
        }
      },
      {
        "artist": {
          "mbid": "58b599cd-b1de-45e3-863a-3b54194a0f20",
          "#text": "HONNE"
        },
        "streamable": "0",
        "image": [
          {
            "size": "small",
            "#text": "https://lastfm.freetls.fastly.net/i/u/34s/c260375c060b8f33d5412b38e9167d30.jpg"
          },
          {
            "size": "medium",
            "#text": "https://lastfm.freetls.fastly.net/i/u/64s/c260375c060b8f33d5412b38e9167d30.jpg"
          },
          {
            "size": "large",
            "#text": "https://lastfm.freetls.fastly.net/i/u/174s/c260375c060b8f33d5412b38e9167d30.jpg"
          },
          {
            "size": "extralarge",
            "#text": "https://lastfm.freetls.fastly.net/i/u/300x300/c260375c060b8f33d5412b38e9167d30.jpg"
          }
        ],
        "mbid": "",
        "album": {
          "mbid": "44dec69a-c8b4-4be0-90de-d8fa70980365",
          "#text": "LET\u2019S JUST SAY THE WORLD ENDED A WEEK FROM NOW, WHAT WOULD YOU DO? (DELUXE)"
        },
        "name": "BACK ON TOP (feat. Griff)",
        "url": "https://www.last.fm/music/HONNE/_/BACK+ON+TOP+(feat.+Griff)",
        "date": {
          "uts": "1742055175",
          "#text": "15 Mar 2025, 16:12"
        }
      }
    ],
    "@attr": {
      "user": "injoon5",
      "totalPages": "133",
      "page": "1",
      "perPage": "50",
      "total": "6630"
    }
  }
}