{
  "recenttracks": {
    "track": [
      {
        "artist": {
          "mbid": "c0ef2ba5-a7b7-40ea-bd27-30acccfcac11",
          "#text": "Lauv"
        },
        "streamable": "0",
        "image": [
          {
            "size": "small",
            "#text": "https://lastfm.freetls.fastly.net/i/u/34s/fff716db0b935ab873c03e7b95fca9e3.jpg"
          },
          {
            "size": "medium",
            "#text": "https://lastfm.freetls.fastly.net/i/u/64s/fff716db0b935ab873c03e7b95fca9e3.jpg"
          },
          {
            "size": "large",
            "#text": "https://lastfm.freetls.fastly.net/i/u/174s/fff716db0b935ab873c03e7b95fca9e3.jpg"
          },
          {
            "size": "extralarge",
            "#text": "https://lastfm.freetls.fastly.net/i/u/300x300/fff716db0b935ab873c03e7b95fca9e3.jpg"
          }
        ],
        "mbid": "0e661800-6fc1-4850-9699-63620c8729e3",
        "album": {
          "mbid": "10540bc4-38c8-498d-83e3-5c7b23a5245e",
          "#text": "~how i'm feeling~"
        },
        "name": "Invisible Things",
        "@attr": {
          "nowplaying": "true"
        },
        "url": "https://www.last.fm/music/Lauv/_/Invisible+Things"
      },
      {
        "artist": {
          "mbid": "c0ef2ba5-a7b7-40ea-bd27-30acccfcac11",
          "#text": "Lauv"
        },
        "streamable": "0",
        "image": [
          {
            "size": "small",
            "#text": "https://lastfm.freetls.fastly.net/i/u/34s/fff716db0b935ab873c03e7b95fca9e3.jpg"
          },
          {
            "size": "medium",
            "#text": "https://lastfm.freetls.fastly.net/i/u/64s/fff716db0b935ab873c03e7b95fca9e3.jpg"
          },
          {
            "size": "large",
            "#text": "https://lastfm.freetls.fastly.net/i/u/174s/fff716db0b935ab873c03e7b95fca9e3.jpg"
          },
          {
            "size": "extralarge",
            "#text": "https://lastfm.freetls.fastly.net/i/u/300x300/fff716db0b935ab873c03e7b95fca9e3.jpg"
          }
        ],
        "mbid": "0e661800-6fc1-4850-9699-63620c8729e3",
        "album": {
          "mbid": "10540bc4-38c8-498d-83e3-5c7b23a5245e",
          "#text": "~how i'm feeling~"
        },
        "name": "Invisible Things",
        "url": "https://www.last.fm/music/Lauv/_/Invisible+Things",
        "date": {
          "uts": "1717501001",
          "#text": "04 Jun 2024, 11:36"
        }
      },
      {
        "artist": {
          "mbid": "",
          "#text": "henry moodie"
        },
        "streamable": "0",
        "image": [
          {
            "size": "small",
            "#text": "https://lastfm.freetls.fastly.net/i/u/34s/5ca2d6c58db2aadb5676f9e5d41fd58d.jpg"
          },
          {
            "size": "medium",
            "#text": "https://lastfm.freetls.fastly.net/i/u/64s/5ca2d6c58db2aadb5676f9e5d41fd58d.jpg"
          },
          {
            "size": "large",
            "#text": "https://lastfm.freetls.fastly.net/i/u/174s/5ca2d6c58db2aadb5676f9e5d41fd58d.jpg"
          },
          {
            "size": "extralarge",
            "#text": "https://lastfm.freetls.fastly.net/i/u/300x300/5ca2d6c58db2aadb5676f9e5d41fd58d.jpg"
          }
        ],
        "mbid": "d83d68f7-c540-4de2-9313-e607296260d5",
        "album": {
          "mbid": "",
          "#text": "drunk text - Single"
        },
        "name": "drunk text",
        "url": "https://www.last.fm/music/henry+moodie/_/drunk+text",
        "date": {
          "uts": "1717500809",
          "#text": "04 Jun 2024, 11:33"
        }
      },
      {
        "artist": {
          "mbid": "be465d46-9615-4722-b828-ea531ff97ea3",
          "#text": "John K"
        },
        "streamable": "0",
        "image": [
          {
            "size": "small",
            "#text": "https://lastfm.freetls.fastly.net/i/u/34s/d8b40e6451329f64db72534fb30e1879.jpg"
          },
          {
            "size": "medium",
            "#text": "https://lastfm.freetls.fastly.net/i/u/64s/d8b40e6451329f64db72534fb30e1879.jpg"
          },
          {
            "size": "large",
            "#text": "https://lastfm.freetls.fastly.net/i/u/174s/d8b40e6451329f64db72534fb30e1879.jpg"
          },
          {
            "size": "extralarge",
            "#text": "https://lastfm.freetls.fastly.net/i/u/300x300/d8b40e6451329f64db72534fb30e1879.jpg"
          }
        ],
        "mbid": "",
        "album": {
          "mbid": "",
          "#text": "love + everything else"
        },
        "name": "parachute",
        "url": "https://www.last.fm/music/John+K/_/parachute",
        "date": {
          "uts": "1717500635",
          "#text": "04 Jun 2024, 11:30"
        }
      },
      {
        "artist": {
          "mbid": "8ce77888-cd3b-4014-b710-88f83ec93633",
          "#text": "MAX & Ali Gatie"
        },
        "streamable": "0",
        "image": [
          {
            "size": "small",
            "#text": "https://lastfm.freetls.fastly.net/i/u/34s/b185bb240b26000619afa912285064a0.jpg"
          },
          {
            "size": "medium",
            "#text": "https://lastfm.freetls.fastly.net/i/u/64s/b185bb240b26000619afa912285064a0.jpg"
          },
          {
            "size": "large",
            "#text": "https://lastfm.freetls.fastly.net/i/u/174s/b185bb240b26000619afa912285064a0.jpg"
          },
          {
            "size": "extralarge",
            "#text": "https://lastfm.freetls.fastly.net/i/u/300x300/b185bb240b26000619afa912285064a0.jpg"
          }
        ],
        "mbid": "01ecf35e-f974-4cac-9c2c-74f7085560bb",
        "album": {
          "mbid": "",
          "#text": "WHO HURT YOU? (Deluxe)"
        },
        "name": "Butterflies",
        "url": "https://www.last.fm/music/MAX+&+Ali+Gatie/_/Butterflies",
        "date": {
          "uts": "1717500461",
          "#text": "04 Jun 2024, 11:27"
        }
      },
      {
        "artist": {
          "mbid": "b8a7c51f-362c-4dcb-a259-bc6e0095f0a6",
          "#text": "Ed Sheeran"
        },
        "streamable": "0",
        "image": [
          {
            "size": "small",
            "#text": "https://lastfm.freetls.fastly.net/i/u/34s/355b0e1174e7c72669cf82f2382115e2.jpg"
          },
          {
            "size": "medium",
            "#text": "https://lastfm.freetls.fastly.net/i/u/64s/355b0e1174e7c72669cf82f2382115e2.jpg"
          },
          {
            "size": "large",
            "#text": "https://lastfm.freetls.fastly.net/i/u/174s/355b0e1174e7c72669cf82f2382115e2.jpg"
          },
          {
            "size": "extralarge",
            "#text": "https://lastfm.freetls.fastly.net/i/u/300x300/355b0e1174e7c72669cf82f2382115e2.jpg"
          }
        ],
        "mbid": "7dcbc1be-4257-4d64-b915-045dfb23ae88",
        "album": {
          "mbid": "3ec0cc3a-d3ff-4dff-8509-a133637debca",
          "#text": "x (Deluxe Edition)"
        },
        "name": "Photograph",
        "url": "https://www.last.fm/music/Ed+Sheeran/_/Photograph",
        "date": {
          "uts": "1717498827",
          "#text": "04 Jun 2024, 11:00"
        }
      },
      {
        "artist": {
          "mbid": "e0140a67-e4d1-4f13-8a01-364355bee46e",
          "#text": "Justin Bieber"
        },
        "streamable": "0",
        "image": [
          {
            "size": "small",
            "#text": "https://lastfm.freetls.fastly.net/i/u/34s/4e8d12ff15734425e137ebe57c2c9a0e.jpg"
          },
          {
            "size": "medium",
            "#text": "https://lastfm.freetls.fastly.net/i/u/64s/4e8d12ff15734425e137ebe57c2c9a0e.jpg"
          },
          {
            "size": "large",
            "#text": "https://lastfm.freetls.fastly.net/i/u/174s/4e8d12ff15734425e137ebe57c2c9a0e.jpg"
          },
          {
            "size": "extralarge",
            "#text": "https://lastfm.freetls.fastly.net/i/u/300x300/4e8d12ff15734425e137ebe57c2c9a0e.jpg"
          }
        ],
        "mbid": "",
        "album": {
          "mbid": "24280154-2ae7-4d2d-bf2b-9bf73be8a1cd",
          "#text": "Justice (The Complete Edition)"
        },
        "name": "Hold On",
        "url": "https://www.last.fm/music/Justin+Bieber/_/Hold+On",
        "date": {
          "uts": "1717498610",
          "#text": "04 Jun 2024, 10:56"
        }
      },
      {
        "artist": {
          "mbid": "ad279295-653f-42e1-9aaa-b731df2e78ba",
          "#text": "Owl City"
        },
        "streamable": "0",
        "image": [
          {
            "size": "small",
            "#text": "https://lastfm.freetls.fastly.net/i/u/34s/71a14744ae084406afed2566027b5f1c.png"
          },
          {
            "size": "medium",
            "#text": "https://lastfm.freetls.fastly.net/i/u/64s/71a14744ae084406afed2566027b5f1c.png"
          },
          {
            "size": "large",
            "#text": "https://lastfm.freetls.fastly.net/i/u/174s/71a14744ae084406afed2566027b5f1c.png"
          },
          {
            "size": "extralarge",
            "#text": "https://lastfm.freetls.fastly.net/i/u/300x300/71a14744ae084406afed2566027b5f1c.png"
          }
        ],
        "mbid": "",
        "album": {
          "mbid": "",
          "#text": "Ocean Eyes (Deluxe Version)"
        },
        "name": "Fireflies",
        "url": "https://www.last.fm/music/Owl+City/_/Fireflies",
        "date": {
          "uts": "1717498411",
          "#text": "04 Jun 2024, 10:53"
        }
      },
      {
        "artist": {
          "mbid": "",
          "#text": "VaultBoy"
        },
        "streamable": "0",
        "image": [
          {
            "size": "small",
            "#text": "https://lastfm.freetls.fastly.net/i/u/34s/349d8499cb6a398c698fd3ed3839afaf.jpg"
          },
          {
            "size": "medium",
            "#text": "https://lastfm.freetls.fastly.net/i/u/64s/349d8499cb6a398c698fd3ed3839afaf.jpg"
          },
          {
            "size": "large",
            "#text": "https://lastfm.freetls.fastly.net/i/u/174s/349d8499cb6a398c698fd3ed3839afaf.jpg"
          },
          {
            "size": "extralarge",
            "#text": "https://lastfm.freetls.fastly.net/i/u/300x300/349d8499cb6a398c698fd3ed3839afaf.jpg"
          }
        ],
        "mbid": "f9e9f59b-fa57-43a8-ba6d-5a4c28769e67",
        "album": {
          "mbid": "",
          "#text": "everything and nothing"
        },
        "name": "closer (feat. salem ilese)",
        "url": "https://www.last.fm/music/VaultBoy/_/closer+(feat.+salem+ilese)",
        "date": {
          "uts": "1717498209",
          "#text": "04 Jun 2024, 10:50"
        }
      },
      {
        "artist": {
          "mbid": "dc303714-d974-4a5c-b0c4-4c489c99322f",
          "#text": "The Ivy"
        },
        "streamable": "0",
        "image": [
          {
            "size": "small",
            "#text": "https://lastfm.freetls.fastly.net/i/u/34s/2a96cbd8b46e442fc41c2b86b821562f.png"
          },
          {
            "size": "medium",
            "#text": "https://lastfm.freetls.fastly.net/i/u/64s/2a96cbd8b46e442fc41c2b86b821562f.png"
          },
          {
            "size": "large",
            "#text": "https://lastfm.freetls.fastly.net/i/u/174s/2a96cbd8b46e442fc41c2b86b821562f.png"
          },
          {
            "size": "extralarge",
            "#text": "https://lastfm.freetls.fastly.net/i/u/300x300/2a96cbd8b46e442fc41c2b86b821562f.png"
          }
        ],
        "mbid": "",
        "album": {
          "mbid": "",
          "#text": "Better in My Head - Single"
        },
        "name": "Better in My Head",
        "url": "https://www.last.fm/music/The+Ivy/_/Better+in+My+Head",
        "date": {
          "uts": "1717497083",
          "#text": "04 Jun 2024, 10:31"
        }
      },
      {
        "artist": {
          "mbid": "7eb1ce54-a355-41f9-8d68-e018b096d427",
          "#text": "Harry Styles"
        },
        "streamable": "0",
        "image": [
          {
            "size": "small",
            "#text": "https://lastfm.freetls.fastly.net/i/u/34s/931b66df2652b311fb1078ac189a2e96.jpg"
          },
          {
            "size": "medium",
            "#text": "https://lastfm.freetls.fastly.net/i/u/64s/931b66df2652b311fb1078ac189a2e96.jpg"
          },
          {
            "size": "large",
            "#text": "https://lastfm.freetls.fastly.net/i/u/174s/931b66df2652b311fb1078ac189a2e96.jpg"
          },
          {
            "size": "extralarge",
            "#text": "https://lastfm.freetls.fastly.net/i/u/300x300/931b66df2652b311fb1078ac189a2e96.jpg"
          }
        ],
        "mbid": "2df03232-d68c-4aa1-9b87-a3fa0a35bd2a",
        "album": {
          "mbid": "6d8f2455-baa3-423c-8607-b7ea4a560fe3",
          "#text": "Harry's House"
        },
        "name": "Satellite",
        "url": "https://www.last.fm/music/Harry+Styles/_/Satellite",
        "date": {
          "uts": "1717496872",
          "#text": "04 Jun 2024, 10:27"
        }
      },
      {
        "artist": {
          "mbid": "f1cc066a-6dd1-4b18-ae68-3708472ab4b1",
          "#text": "Lany"
        },
        "streamable": "0",
        "image": [
          {
            "size": "small",
            "#text": "https://lastfm.freetls.fastly.net/i/u/34s/f05bb1eb0c675aee90af90dc5c544397.jpg"
          },
          {
            "size": "medium",
            "#text": "https://lastfm.freetls.fastly.net/i/u/64s/f05bb1eb0c675aee90af90dc5c544397.jpg"
          },
          {
            "size": "large",
            "#text": "https://lastfm.freetls.fastly.net/i/u/174s/f05bb1eb0c675aee90af90dc5c544397.jpg"
          },
          {
            "size": "extralarge",
            "#text": "https://lastfm.freetls.fastly.net/i/u/300x300/f05bb1eb0c675aee90af90dc5c544397.jpg"
          }
        ],
        "mbid": "dd2098c2-8f3e-4e0e-beef-a92dfbaee7e5",
        "album": {
          "mbid": "1eddad44-aebc-49b7-903b-08de6ae225ff",
          "#text": "LANY"
        },
        "name": "Super Far",
        "url": "https://www.last.fm/music/Lany/_/Super+Far",
        "date": {
          "uts": "1717496660",
          "#text": "04 Jun 2024, 10:24"
        }
      },
      {
        "artist": {
          "mbid": "e116e0be-c371-4d57-bc09-e2d762d82540",
          "#text": "Jeremy Zucker"
        },
        "streamable": "0",
        "image": [
          {
            "size": "small",
            "#text": "https://lastfm.freetls.fastly.net/i/u/34s/40f6cc46ee3bae5a3857ecf771a80a9e.jpg"
          },
          {
            "size": "medium",
            "#text": "https://lastfm.freetls.fastly.net/i/u/64s/40f6cc46ee3bae5a3857ecf771a80a9e.jpg"
          },
          {
            "size": "large",
            "#text": "https://lastfm.freetls.fastly.net/i/u/174s/40f6cc46ee3bae5a3857ecf771a80a9e.jpg"
          },
          {
            "size": "extralarge",
            "#text": "https://lastfm.freetls.fastly.net/i/u/300x300/40f6cc46ee3bae5a3857ecf771a80a9e.jpg"
          }
        ],
        "mbid": "aa36d936-68d8-4c9a-a74d-5266a7319f34",
        "album": {
          "mbid": "",
          "#text": "glisten - EP"
        },
        "name": "all the kids are depressed",
        "url": "https://www.last.fm/music/Jeremy+Zucker/_/all+the+kids+are+depressed",
        "date": {
          "uts": "1717496472",
          "#text": "04 Jun 2024, 10:21"
        }
      },
      {
        "artist": {
          "mbid": "f1cc066a-6dd1-4b18-ae68-3708472ab4b1",
          "#text": "Lany"
        },
        "streamable": "0",
        "image": [
          {
            "size": "small",
            "#text": "https://lastfm.freetls.fastly.net/i/u/34s/b6c33ae7215181697acfb8fde7780b20.jpg"
          },
          {
            "size": "medium",
            "#text": "https://lastfm.freetls.fastly.net/i/u/64s/b6c33ae7215181697acfb8fde7780b20.jpg"
          },
          {
            "size": "large",
            "#text": "https://lastfm.freetls.fastly.net/i/u/174s/b6c33ae7215181697acfb8fde7780b20.jpg"
          },
          {
            "size": "extralarge",
            "#text": "https://lastfm.freetls.fastly.net/i/u/300x300/b6c33ae7215181697acfb8fde7780b20.jpg"
          }
        ],
        "mbid": "02c44f63-031e-4937-a405-b302d588cf83",
        "album": {
          "mbid": "184d08b5-1e0e-45ba-9dd1-ff2a912c4dfb",
          "#text": "gg bb xx (deluxe)"
        },
        "name": "dna",
        "url": "https://www.last.fm/music/Lany/_/dna",
        "date": {
          "uts": "1717496293",
          "#text": "04 Jun 2024, 10:18"
        }
      },
      {
        "artist": {
          "mbid": "dc303714-d974-4a5c-b0c4-4c489c99322f",
          "#text": "The Ivy"
        },
        "streamable": "0",
        "image": [
          {
            "size": "small",
            "#text": "https://lastfm.freetls.fastly.net/i/u/34s/2a96cbd8b46e442fc41c2b86b821562f.png"
          },
          {
            "size": "medium",
            "#text": "https://lastfm.freetls.fastly.net/i/u/64s/2a96cbd8b46e442fc41c2b86b821562f.png"
          },
          {
            "size": "large",
            "#text": "https://lastfm.freetls.fastly.net/i/u/174s/2a96cbd8b46e442fc41c2b86b821562f.png"
          },
          {
            "size": "extralarge",
            "#text": "https://lastfm.freetls.fastly.net/i/u/300x300/2a96cbd8b46e442fc41c2b86b821562f.png"
          }
        ],
        "mbid": "",
        "album": {
          "mbid": "",
          "#text": "Have You Ever Been in Love - Single"
        },
        "name": "Have You Ever Been in Love",
        "url": "https://www.last.fm/music/The+Ivy/_/Have+You+Ever+Been+in+Love",
        "date": {
          "uts": "1717496100",
          "#text": "04 Jun 2024, 10:15"
        }
      },
      {
        "artist": {
          "mbid": "525f1f1c-03f0-4bc8-8dfd-e7521f87631b",
          "#text": "Charlie Puth"
        },
        "streamable": "0",
        "image": [
          {
            "size": "small",
            "#text": "https://lastfm.freetls.fastly.net/i/u/34s/1f4d106bfc5a4d0e8dcec8490630fab3.jpg"
          },
          {
            "size": "medium",
            "#text": "https://lastfm.freetls.fastly.net/i/u/64s/1f4d106bfc5a4d0e8dcec8490630fab3.jpg"
          },
          {
            "size": "large",
            "#text": "https://lastfm.freetls.fastly.net/i/u/174s/1f4d106bfc5a4d0e8dcec8490630fab3.jpg"
          },
          {
            "size": "extralarge",
            "#text": "https://lastfm.freetls.fastly.net/i/u/300x300/1f4d106bfc5a4d0e8dcec8490630fab3.jpg"
          }
        ],
        "mbid": "14dbb322-1417-42da-909e-7381b867fd38",
        "album": {
          "mbid": "f1df0b2e-d00c-4686-810d-1f633ecb4aee",
          "#text": "CHARLIE"
        },
        "name": "Charlie Be Quiet!",
        "url": "https://www.last.fm/music/Charlie+Puth/_/Charlie+Be+Quiet!",
        "date": {
          "uts": "1717495932",
          "#text": "04 Jun 2024, 10:12"
        }
      },
      {
        "artist": {
          "mbid": "e0140a67-e4d1-4f13-8a01-364355bee46e",
          "#text": "Justin Bieber"
        },
        "streamable": "0",
        "image": [
          {
            "size": "small",
            "#text": "https://lastfm.freetls.fastly.net/i/u/34s/4e8d12ff15734425e137ebe57c2c9a0e.jpg"
          },
          {
            "size": "medium",
            "#text": "https://lastfm.freetls.fastly.net/i/u/64s/4e8d12ff15734425e137ebe57c2c9a0e.jpg"
          },
          {
            "size": "large",
            "#text": "https://lastfm.freetls.fastly.net/i/u/174s/4e8d12ff15734425e137ebe57c2c9a0e.jpg"
          },
          {
            "size": "extralarge",
            "#text": "https://lastfm.freetls.fastly.net/i/u/300x300/4e8d12ff15734425e137ebe57c2c9a0e.jpg"
          }
        ],
        "mbid": "",
        "album": {
          "mbid": "24280154-2ae7-4d2d-bf2b-9bf73be8a1cd",
          "#text": "Justice (The Complete Edition)"
        },
        "name": "Peaches (feat. Daniel Caesar & GIV\u0112ON)",
        "url": "https://www.last.fm/music/Justin+Bieber/_/Peaches+(feat.+Daniel+Caesar+&+GIV%C4%92ON)",
        "date": {
          "uts": "1717495767",
          "#text": "04 Jun 2024, 10:09"
        }
      },
      {
        "artist": {
          "mbid": "be465d46-9615-4722-b828-ea531ff97ea3",
          "#text": "John K"
        },
        "streamable": "0",
        "image": [
          {
            "size": "small",
            "#text": "https://lastfm.freetls.fastly.net/i/u/34s/d8b40e6451329f64db72534fb30e1879.jpg"
          },
          {
            "size": "medium",
            "#text": "https://lastfm.freetls.fastly.net/i/u/64s/d8b40e6451329f64db72534fb30e1879.jpg"
          },
          {
            "size": "large",
            "#text": "https://lastfm.freetls.fastly.net/i/u/174s/d8b40e6451329f64db72534fb30e1879.jpg"
          },
          {
            "size": "extralarge",
            "#text": "https://lastfm.freetls.fastly.net/i/u/300x300/d8b40e6451329f64db72534fb30e1879.jpg"
          }
        ],
        "mbid": "",
        "album": {
          "mbid": "",
          "#text": "love + everything else"
        },
        "name": "if we never met",
        "url": "https://www.last.fm/music/John+K/_/if+we+never+met",
        "date": {
          "uts": "1717495554",
          "#text": "04 Jun 2024, 10:05"
        }
      },
      {
        "artist": {
          "mbid": "f1cc066a-6dd1-4b18-ae68-3708472ab4b1",
          "#text": "Lany"
        },
        "streamable": "0",
        "image": [
          {
            "size": "small",
            "#text": "https://lastfm.freetls.fastly.net/i/u/34s/27e554ae95df2e266bafcddddc084f33.jpg"
          },
          {
            "size": "medium",
            "#text": "https://lastfm.freetls.fastly.net/i/u/64s/27e554ae95df2e266bafcddddc084f33.jpg"
          },
          {
            "size": "large",
            "#text": "https://lastfm.freetls.fastly.net/i/u/174s/27e554ae95df2e266bafcddddc084f33.jpg"
          },
          {
            "size": "extralarge",
            "#text": "https://lastfm.freetls.fastly.net/i/u/300x300/27e554ae95df2e266bafcddddc084f33.jpg"
          }
        ],
        "mbid": "05479945-d8e0-473a-b6b5-25bfa0759077",
        "album": {
          "mbid": "59b026dd-4191-42a4-885a-b6926c06b69f",
          "#text": "gg bb xx"
        },
        "name": "up to me",
        "url": "https://www.last.fm/music/Lany/_/up+to+me",
        "date": {
          "uts": "1717495389",
          "#text": "04 Jun 2024, 10:03"
        }
      },
      {
        "artist": {
          "mbid": "",
          "#text": "Yorke & joan"
        },
        "streamable": "0",
        "image": [
          {
            "size": "small",
            "#text": "https://lastfm.freetls.fastly.net/i/u/34s/95d66fcae200650a5e6ac8014f745363.jpg"
          },
          {
            "size": "medium",
            "#text": "https://lastfm.freetls.fastly.net/i/u/64s/95d66fcae200650a5e6ac8014f745363.jpg"
          },
          {
            "size": "large",
            "#text": "https://lastfm.freetls.fastly.net/i/u/174s/95d66fcae200650a5e6ac8014f745363.jpg"
          },
          {
            "size": "extralarge",
            "#text": "https://lastfm.freetls.fastly.net/i/u/300x300/95d66fcae200650a5e6ac8014f745363.jpg"
          }
        ],
        "mbid": "",
        "album": {
          "mbid": "",
          "#text": "ten feet tall - EP"
        },
        "name": "Window Shopping",
        "url": "https://www.last.fm/music/Yorke+&+joan/_/Window+Shopping",
        "date": {
          "uts": "1717495203",
          "#text": "04 Jun 2024, 10:00"
        }
      },
      {
        "artist": {
          "mbid": "f64330ed-5814-480b-ad24-968e7a21ba14",
          "#text": "AJ Mitchell"
        },
        "streamable": "0",
        "image": [
          {
            "size": "small",
            "#text": "https://lastfm.freetls.fastly.net/i/u/34s/0402041600a6bf6cf8249e2f5aa1e5f6.png"
          },
          {
            "size": "medium",
            "#text": "https://lastfm.freetls.fastly.net/i/u/64s/0402041600a6bf6cf8249e2f5aa1e5f6.png"
          },
          {
            "size": "large",
            "#text": "https://lastfm.freetls.fastly.net/i/u/174s/0402041600a6bf6cf8249e2f5aa1e5f6.png"
          },
          {
            "size": "extralarge",
            "#text": "https://lastfm.freetls.fastly.net/i/u/300x300/0402041600a6bf6cf8249e2f5aa1e5f6.png"
          }
        ],
        "mbid": "",
        "album": {
          "mbid": "",
          "#text": "Like Strangers Do - Single"
        },
        "name": "Like Strangers Do",
        "url": "https://www.last.fm/music/AJ+Mitchell/_/Like+Strangers+Do",
        "date": {
          "uts": "1717495022",
          "#text": "04 Jun 2024, 09:57"
        }
      },
      {
        "artist": {
          "mbid": "994fd4c8-a7d0-4a08-9f3a-7ad22aadd437",
          "#text": "Joan"
        },
        "streamable": "0",
        "image": [
          {
            "size": "small",
            "#text": "https://lastfm.freetls.fastly.net/i/u/34s/1abaa483a3e4f9193b74525fd2d563d6.jpg"
          },
          {
            "size": "medium",
            "#text": "https://lastfm.freetls.fastly.net/i/u/64s/1abaa483a3e4f9193b74525fd2d563d6.jpg"
          },
          {
            "size": "large",
            "#text": "https://lastfm.freetls.fastly.net/i/u/174s/1abaa483a3e4f9193b74525fd2d563d6.jpg"
          },
          {
            "size": "extralarge",
            "#text": "https://lastfm.freetls.fastly.net/i/u/300x300/1abaa483a3e4f9193b74525fd2d563d6.jpg"
          }
        ],
        "mbid": "0ba86acb-1399-485a-a28b-6a95494c96bc",
        "album": {
          "mbid": "",
          "#text": "Love Somebody Like You - Single"
        },
        "name": "love somebody like you",
        "url": "https://www.last.fm/music/Joan/_/love+somebody+like+you",
        "date": {
          "uts": "1717494827",
          "#text": "04 Jun 2024, 09:53"
        }
      },
      {
        "artist": {
          "mbid": "f1cc066a-6dd1-4b18-ae68-3708472ab4b1",
          "#text": "Lany"
        },
        "streamable": "0",
        "image": [
          {
            "size": "small",
            "#text": "https://lastfm.freetls.fastly.net/i/u/34s/4b0641d0b3dcb6368329eb05adc61072.jpg"
          },
          {
            "size": "medium",
            "#text": "https://lastfm.freetls.fastly.net/i/u/64s/4b0641d0b3dcb6368329eb05adc61072.jpg"
          },
          {
            "size": "large",
            "#text": "https://lastfm.freetls.fastly.net/i/u/174s/4b0641d0b3dcb6368329eb05adc61072.jpg"
          },
          {
            "size": "extralarge",
            "#text": "https://lastfm.freetls.fastly.net/i/u/300x300/4b0641d0b3dcb6368329eb05adc61072.jpg"
          }
        ],
        "mbid": "37873dff-b187-459e-b620-1b74b1d4fcf7",
        "album": {
          "mbid": "",
          "#text": "Lany (Deluxe)"
        },
        "name": "13",
        "url": "https://www.last.fm/music/Lany/_/13",
        "date": {
          "uts": "1717494595",
          "#text": "04 Jun 2024, 09:49"
        }
      },
      {
        "artist": {
          "mbid": "b7d92248-97e3-4450-8057-6fe06738f735",
          "#text": "Shawn Mendes"
        },
        "streamable": "0",
        "image": [
          {
            "size": "small",
            "#text": "https://lastfm.freetls.fastly.net/i/u/34s/87de33650984273a54786a0fe33fefb4.png"
          },
          {
            "size": "medium",
            "#text": "https://lastfm.freetls.fastly.net/i/u/64s/87de33650984273a54786a0fe33fefb4.png"
          },
          {
            "size": "large",
            "#text": "https://lastfm.freetls.fastly.net/i/u/174s/87de33650984273a54786a0fe33fefb4.png"
          },
          {
            "size": "extralarge",
            "#text": "https://lastfm.freetls.fastly.net/i/u/300x300/87de33650984273a54786a0fe33fefb4.png"
          }
        ],
        "mbid": "",
        "album": {
          "mbid": "",
          "#text": "If I Can't Have You - Single"
        },
        "name": "If I Can't Have You",
        "url": "https://www.last.fm/music/Shawn+Mendes/_/If+I+Can%27t+Have+You",
        "date": {
          "uts": "1717494378",
          "#text": "04 Jun 2024, 09:46"
        }
      },
      {
        "artist": {
          "mbid": "c0ef2ba5-a7b7-40ea-bd27-30acccfcac11",
          "#text": "Lauv"
        },
        "streamable": "0",
        "image": [
          {
            "size": "small",
            "#text": "https://lastfm.freetls.fastly.net/i/u/34s/1191e058732a5bb5eb8722e09330a58b.jpg"
          },
          {
            "size": "medium",
            "#text": "https://lastfm.freetls.fastly.net/i/u/64s/1191e058732a5bb5eb8722e09330a58b.jpg"
          },
          {
            "size": "large",
            "#text": "https://lastfm.freetls.fastly.net/i/u/174s/1191e058732a5bb5eb8722e09330a58b.jpg"
          },
          {
            "size": "extralarge",
            "#text": "https://lastfm.freetls.fastly.net/i/u/300x300/1191e058732a5bb5eb8722e09330a58b.jpg"
          }
        ],
        "mbid": "13ad1a5c-458a-47d3-aba6-0d2e6727fac0",
        "album": {
          "mbid": "",
          "#text": "I met you when I was 18. (the playlist)"
        },
        "name": "Paris in the Rain",
        "url": "https://www.last.fm/music/Lauv/_/Paris+in+the+Rain",
        "date": {
          "uts": "1717494180",
          "#text": "04 Jun 2024, 09:43"
        }
      },
      {
        "artist": {
          "mbid": "c0ef2ba5-a7b7-40ea-bd27-30acccfcac11",
          "#text": "Lauv"
        },
        "streamable": "0",
        "image": [
          {
            "size": "small",
            "#text": "https://lastfm.freetls.fastly.net/i/u/34s/fff716db0b935ab873c03e7b95fca9e3.jpg"
          },
          {
            "size": "medium",
            "#text": "https://lastfm.freetls.fastly.net/i/u/64s/fff716db0b935ab873c03e7b95fca9e3.jpg"
          },
          {
            "size": "large",
            "#text": "https://lastfm.freetls.fastly.net/i/u/174s/fff716db0b935ab873c03e7b95fca9e3.jpg"
          },
          {
            "size": "extralarge",
            "#text": "https://lastfm.freetls.fastly.net/i/u/300x300/fff716db0b935ab873c03e7b95fca9e3.jpg"
          }
        ],
        "mbid": "0ae5cedc-2ef4-4c7d-91b2-cd639f05f896",
        "album": {
          "mbid": "10540bc4-38c8-498d-83e3-5c7b23a5245e",
          "#text": "~how i'm feeling~"
        },
        "name": "Lonely Eyes",
        "url": "https://www.last.fm/music/Lauv/_/Lonely+Eyes",
        "date": {
          "uts": "1717493979",
          "#text": "04 Jun 2024, 09:39"
        }
      },
      {
        "artist": {
          "mbid": "",
          "#text": "Sam Smith & Normani"
        },
        "streamable": "0",
        "image": [
          {
            "size": "small",
            "#text": "https://lastfm.freetls.fastly.net/i/u/34s/92fdc5a5fdb8cd05a49437f7eb8bf879.jpg"
          },
          {
            "size": "medium",
            "#text": "https://lastfm.freetls.fastly.net/i/u/64s/92fdc5a5fdb8cd05a49437f7eb8bf879.jpg"
          },
          {
            "size": "large",
            "#text": "https://lastfm.freetls.fastly.net/i/u/174s/92fdc5a5fdb8cd05a49437f7eb8bf879.jpg"
          },
          {
            "size": "extralarge",
            "#text": "https://lastfm.freetls.fastly.net/i/u/300x300/92fdc5a5fdb8cd05a49437f7eb8bf879.jpg"
          }
        ],
        "mbid": "5e3652ca-1e7f-4a5e-ad7a-d825432c99e2",
        "album": {
          "mbid": "",
          "#text": "Dancing with a Stranger - Single"
        },
        "name": "Dancing With A Stranger",
        "url": "https://www.last.fm/music/Sam+Smith+&+Normani/_/Dancing+With+A+Stranger",
        "date": {
          "uts": "1717493789",
          "#text": "04 Jun 2024, 09:36"
        }
      },
      {
        "artist": {
          "mbid": "c0ef2ba5-a7b7-40ea-bd27-30acccfcac11",
          "#text": "Lauv"
        },
        "streamable": "0",
        "image": [
          {
            "size": "small",
            "#text": "https://lastfm.freetls.fastly.net/i/u/34s/fff716db0b935ab873c03e7b95fca9e3.jpg"
          },
          {
            "size": "medium",
            "#text": "https://lastfm.freetls.fastly.net/i/u/64s/fff716db0b935ab873c03e7b95fca9e3.jpg"
          },
          {
            "size": "large",
            "#text": "https://lastfm.freetls.fastly.net/i/u/174s/fff716db0b935ab873c03e7b95fca9e3.jpg"
          },
          {
            "size": "extralarge",
            "#text": "https://lastfm.freetls.fastly.net/i/u/300x300/fff716db0b935ab873c03e7b95fca9e3.jpg"
          }
        ],
        "mbid": "8460a4d4-f623-4a0d-82a6-d33d725ab33d",
        "album": {
          "mbid": "10540bc4-38c8-498d-83e3-5c7b23a5245e",
          "#text": "~how i'm feeling~"
        },
        "name": "Sad Forever",
        "url": "https://www.last.fm/music/Lauv/_/Sad+Forever",
        "date": {
          "uts": "1716611070",
          "#text": "25 May 2024, 04:24"
        }
      },
      {
        "artist": {
          "mbid": "f1cc066a-6dd1-4b18-ae68-3708472ab4b1",
          "#text": "Lany"
        },
        "streamable": "0",
        "image": [
          {
            "size": "small",
            "#text": "https://lastfm.freetls.fastly.net/i/u/34s/82ff192be8c416d9518c7779e116597c.jpg"
          },
          {
            "size": "medium",
            "#text": "https://lastfm.freetls.fastly.net/i/u/64s/82ff192be8c416d9518c7779e116597c.jpg"
          },
          {
            "size": "large",
            "#text": "https://lastfm.freetls.fastly.net/i/u/174s/82ff192be8c416d9518c7779e116597c.jpg"
          },
          {
            "size": "extralarge",
            "#text": "https://lastfm.freetls.fastly.net/i/u/300x300/82ff192be8c416d9518c7779e116597c.jpg"
          }
        ],
        "mbid": "19a60ae9-939d-4815-8eb3-1fa4ac356e70",
        "album": {
          "mbid": "70865c0f-601e-4d1d-8ea5-1fcaf284c6c6",
          "#text": "a beautiful blur"
        },
        "name": "Love At First Fight",
        "url": "https://www.last.fm/music/Lany/_/Love+At+First+Fight",
        "date": {
          "uts": "1716571158",
          "#text": "24 May 2024, 17:19"
        }
      },
      {
        "artist": {
          "mbid": "afb680f2-b6eb-4cd7-a70b-a63b25c763d5",
          "#text": "Bruno Mars"
        },
        "streamable": "0",
        "image": [
          {
            "size": "small",
            "#text": "https://lastfm.freetls.fastly.net/i/u/34s/92262af4400a20ae87c278e98d9b41dc.jpg"
          },
          {
            "size": "medium",
            "#text": "https://lastfm.freetls.fastly.net/i/u/64s/92262af4400a20ae87c278e98d9b41dc.jpg"
          },
          {
            "size": "large",
            "#text": "https://lastfm.freetls.fastly.net/i/u/174s/92262af4400a20ae87c278e98d9b41dc.jpg"
          },
          {
            "size": "extralarge",
            "#text": "https://lastfm.freetls.fastly.net/i/u/300x300/92262af4400a20ae87c278e98d9b41dc.jpg"
          }
        ],
        "mbid": "0070ec3b-2f03-46e6-83d5-ae7c5ad11d6e",
        "album": {
          "mbid": "",
          "#text": "Doo-Wops & Hooligans (Deluxe)"
        },
        "name": "Talking to the Moon",
        "url": "https://www.last.fm/music/Bruno+Mars/_/Talking+to+the+Moon",
        "date": {
          "uts": "1716570952",
          "#text": "24 May 2024, 17:15"
        }
      },
      {
        "artist": {
          "mbid": "525f1f1c-03f0-4bc8-8dfd-e7521f87631b",
          "#text": "Charlie Puth"
        },
        "streamable": "0",
        "image": [
          {
            "size": "small",
            "#text": "https://lastfm.freetls.fastly.net/i/u/34s/1f4d106bfc5a4d0e8dcec8490630fab3.jpg"
          },
          {
            "size": "medium",
            "#text": "https://lastfm.freetls.fastly.net/i/u/64s/1f4d106bfc5a4d0e8dcec8490630fab3.jpg"
          },
          {
            "size": "large",
            "#text": "https://lastfm.freetls.fastly.net/i/u/174s/1f4d106bfc5a4d0e8dcec8490630fab3.jpg"
          },
          {
            "size": "extralarge",
            "#text": "https://lastfm.freetls.fastly.net/i/u/300x300/1f4d106bfc5a4d0e8dcec8490630fab3.jpg"
          }
        ],
        "mbid": "a8bdddfe-aafa-46bb-9c68-6ec54f8e9eb4",
        "album": {
          "mbid": "f1df0b2e-d00c-4686-810d-1f633ecb4aee",
          "#text": "CHARLIE"
        },
        "name": "Smells Like Me",
        "url": "https://www.last.fm/music/Charlie+Puth/_/Smells+Like+Me",
        "date": {
          "uts": "1716570742",
          "#text": "24 May 2024, 17:12"
        }
      },
      {
        "artist": {
          "mbid": "f1cc066a-6dd1-4b18-ae68-3708472ab4b1",
          "#text": "Lany"
        },
        "streamable": "0",
        "image": [
          {
            "size": "small",
            "#text": "https://lastfm.freetls.fastly.net/i/u/34s/27e554ae95df2e266bafcddddc084f33.jpg"
          },
          {
            "size": "medium",
            "#text": "https://lastfm.freetls.fastly.net/i/u/64s/27e554ae95df2e266bafcddddc084f33.jpg"
          },
          {
            "size": "large",
            "#text": "https://lastfm.freetls.fastly.net/i/u/174s/27e554ae95df2e266bafcddddc084f33.jpg"
          },
          {
            "size": "extralarge",
            "#text": "https://lastfm.freetls.fastly.net/i/u/300x300/27e554ae95df2e266bafcddddc084f33.jpg"
          }
        ],
        "mbid": "6938dd3c-126e-408d-8c1c-0525cec8c588",
        "album": {
          "mbid": "59b026dd-4191-42a4-885a-b6926c06b69f",
          "#text": "gg bb xx"
        },
        "name": "ex i never had",
        "url": "https://www.last.fm/music/Lany/_/ex+i+never+had",
        "date": {
          "uts": "1716570538",
          "#text": "24 May 2024, 17:08"
        }
      },
      {
        "artist": {
          "mbid": "b1e26560-60e5-4236-bbdb-9aa5a8d5ee19",
          "#text": "Post Malone"
        },
        "streamable": "0",
        "image": [
          {
            "size": "small",
            "#text": "https://lastfm.freetls.fastly.net/i/u/34s/9c2c5b6def1e2a4290f9a00869c85348.jpg"
          },
          {
            "size": "medium",
            "#text": "https://lastfm.freetls.fastly.net/i/u/64s/9c2c5b6def1e2a4290f9a00869c85348.jpg"
          },
          {
            "size": "large",
            "#text": "https://lastfm.freetls.fastly.net/i/u/174s/9c2c5b6def1e2a4290f9a00869c85348.jpg"
          },
          {
            "size": "extralarge",
            "#text": "https://lastfm.freetls.fastly.net/i/u/300x300/9c2c5b6def1e2a4290f9a00869c85348.jpg"
          }
        ],
        "mbid": "4d5ea684-6127-4506-b7b3-c5ea5a1eb1d8",
        "album": {
          "mbid": "61d5cefb-f4f4-4902-b9e0-d9b613225cea",
          "#text": "AUSTIN (Bonus)"
        },
        "name": "Chemical",
        "url": "https://www.last.fm/music/Post+Malone/_/Chemical",
        "date": {
          "uts": "1716570345",
          "#text": "24 May 2024, 17:05"
        }
      },
      {
        "artist": {
          "mbid": "",
          "#text": "Rainbow"
        },
        "streamable": "0",
        "image": [
          {
            "size": "small",
            "#text": "https://lastfm.freetls.fastly.net/i/u/34s/a86702eb67ca3a0cbfca342ad6a0c206.jpg"
          },
          {
            "size": "medium",
            "#text": "https://lastfm.freetls.fastly.net/i/u/64s/a86702eb67ca3a0cbfca342ad6a0c206.jpg"
          },
          {
            "size": "large",
            "#text": "https://lastfm.freetls.fastly.net/i/u/174s/a86702eb67ca3a0cbfca342ad6a0c206.jpg"
          },
          {
            "size": "extralarge",
            "#text": "https://lastfm.freetls.fastly.net/i/u/300x300/a86702eb67ca3a0cbfca342ad6a0c206.jpg"
          }
        ],
        "mbid": "",
        "album": {
          "mbid": "25bbf601-8af6-316b-a54a-87a58b201bd8",
          "#text": "Down to Earth"
        },
        "name": "Since You Been Gone",
        "url": "https://www.last.fm/music/Rainbow/_/Since+You+Been+Gone",
        "date": {
          "uts": "1716570155",
          "#text": "24 May 2024, 17:02"
        }
      },
      {
        "artist": {
          "mbid": "0ee82c4c-f201-4281-b1da-c43c40d168ba",
          "#text": "Josef Salvat"
        },
        "streamable": "0",
        "image": [
          {
            "size": "small",
            "#text": "https://lastfm.freetls.fastly.net/i/u/34s/f62a2d2d433b1f14043655acbafd1302.jpg"
          },
          {
            "size": "medium",
            "#text": "https://lastfm.freetls.fastly.net/i/u/64s/f62a2d2d433b1f14043655acbafd1302.jpg"
          },
          {
            "size": "large",
            "#text": "https://lastfm.freetls.fastly.net/i/u/174s/f62a2d2d433b1f14043655acbafd1302.jpg"
          },
          {
            "size": "extralarge",
            "#text": "https://lastfm.freetls.fastly.net/i/u/300x300/f62a2d2d433b1f14043655acbafd1302.jpg"
          }
        ],
        "mbid": "09655545-e834-4687-9c02-5e90e1cefd5e",
        "album": {
          "mbid": "",
          "#text": "in the afternoon - Single"
        },
        "name": "in the afternoon",
        "url": "https://www.last.fm/music/Josef+Salvat/_/in+the+afternoon",
        "date": {
          "uts": "1716569386",
          "#text": "24 May 2024, 16:49"
        }
      },
      {
        "artist": {
          "mbid": "be465d46-9615-4722-b828-ea531ff97ea3",
          "#text": "John K"
        },
        "streamable": "0",
        "image": [
          {
            "size": "small",
            "#text": "https://lastfm.freetls.fastly.net/i/u/34s/d8b40e6451329f64db72534fb30e1879.jpg"
          },
          {
            "size": "medium",
            "#text": "https://lastfm.freetls.fastly.net/i/u/64s/d8b40e6451329f64db72534fb30e1879.jpg"
          },
          {
            "size": "large",
            "#text": "https://lastfm.freetls.fastly.net/i/u/174s/d8b40e6451329f64db72534fb30e1879.jpg"
          },
          {
            "size": "extralarge",
            "#text": "https://lastfm.freetls.fastly.net/i/u/300x300/d8b40e6451329f64db72534fb30e1879.jpg"
          }
        ],
        "mbid": "",
        "album": {
          "mbid": "",
          "#text": "love + everything else"
        },
        "name": "if we never met",
        "url": "https://www.last.fm/music/John+K/_/if+we+never+met",
        "date": {
          "uts": "1716569213",
          "#text": "24 May 2024, 16:46"
        }
      },
      {
        "artist": {
          "mbid": "28737730-ec70-4da5-89c5-77ac13c5c34d",
          "#text": "Khalid"
        },
        "streamable": "0",
        "image": [
          {
            "size": "small",
            "#text": "https://lastfm.freetls.fastly.net/i/u/34s/20536b4149df70b97dca0e6374a608a3.jpg"
          },
          {
            "size": "medium",
            "#text": "https://lastfm.freetls.fastly.net/i/u/64s/20536b4149df70b97dca0e6374a608a3.jpg"
          },
          {
            "size": "large",
            "#text": "https://lastfm.freetls.fastly.net/i/u/174s/20536b4149df70b97dca0e6374a608a3.jpg"
          },
          {
            "size": "extralarge",
            "#text": "https://lastfm.freetls.fastly.net/i/u/300x300/20536b4149df70b97dca0e6374a608a3.jpg"
          }
        ],
        "mbid": "",
        "album": {
          "mbid": "3a5cbae4-5b58-4428-b278-47d0157f200d",
          "#text": "Free Spirit"
        },
        "name": "Talk (feat. Disclosure)",
        "url": "https://www.last.fm/music/Khalid/_/Talk+(feat.+Disclosure)",
        "date": {
          "uts": "1716569041",
          "#text": "24 May 2024, 16:44"
        }
      },
      {
        "artist": {
          "mbid": "fbf445c0-11ae-4d3e-af1a-c6e2783e447c",
          "#text": "Starship"
        },
        "streamable": "0",
        "image": [
          {
            "size": "small",
            "#text": "https://lastfm.freetls.fastly.net/i/u/34s/e62bbd0522a80cb1cdcd929904f0ef73.png"
          },
          {
            "size": "medium",
            "#text": "https://lastfm.freetls.fastly.net/i/u/64s/e62bbd0522a80cb1cdcd929904f0ef73.png"
          },
          {
            "size": "large",
            "#text": "https://lastfm.freetls.fastly.net/i/u/174s/e62bbd0522a80cb1cdcd929904f0ef73.png"
          },
          {
            "size": "extralarge",
            "#text": "https://lastfm.freetls.fastly.net/i/u/300x300/e62bbd0522a80cb1cdcd929904f0ef73.png"
          }
        ],
        "mbid": "",
        "album": {
          "mbid": "572b6b42-3494-438d-a3d9-0fbf39ebded8",
          "#text": "Knee Deep in the Hoopla"
        },
        "name": "Sara",
        "url": "https://www.last.fm/music/Starship/_/Sara",
        "date": {
          "uts": "1716568796",
          "#text": "24 May 2024, 16:39"
        }
      },
      {
        "artist": {
          "mbid": "e116e0be-c371-4d57-bc09-e2d762d82540",
          "#text": "Jeremy Zucker"
        },
        "streamable": "0",
        "image": [
          {
            "size": "small",
            "#text": "https://lastfm.freetls.fastly.net/i/u/34s/f77479adf0864e8f813758c71896ffda.jpg"
          },
          {
            "size": "medium",
            "#text": "https://lastfm.freetls.fastly.net/i/u/64s/f77479adf0864e8f813758c71896ffda.jpg"
          },
          {
            "size": "large",
            "#text": "https://lastfm.freetls.fastly.net/i/u/174s/f77479adf0864e8f813758c71896ffda.jpg"
          },
          {
            "size": "extralarge",
            "#text": "https://lastfm.freetls.fastly.net/i/u/300x300/f77479adf0864e8f813758c71896ffda.jpg"
          }
        ],
        "mbid": "",
        "album": {
          "mbid": "",
          "#text": "idle - EP"
        },
        "name": "Talk Is Overrated (feat. blackbear)",
        "url": "https://www.last.fm/music/Jeremy+Zucker/_/Talk+Is+Overrated+(feat.+blackbear)",
        "date": {
          "uts": "1716568552",
          "#text": "24 May 2024, 16:35"
        }
      },
      {
        "artist": {
          "mbid": "",
          "#text": "Jeremy Zucker, Lauv & Alexander 23"
        },
        "streamable": "0",
        "image": [
          {
            "size": "small",
            "#text": "https://lastfm.freetls.fastly.net/i/u/34s/c00824189460a093980f0655dd51a3ae.jpg"
          },
          {
            "size": "medium",
            "#text": "https://lastfm.freetls.fastly.net/i/u/64s/c00824189460a093980f0655dd51a3ae.jpg"
          },
          {
            "size": "large",
            "#text": "https://lastfm.freetls.fastly.net/i/u/174s/c00824189460a093980f0655dd51a3ae.jpg"
          },
          {
            "size": "extralarge",
            "#text": "https://lastfm.freetls.fastly.net/i/u/300x300/c00824189460a093980f0655dd51a3ae.jpg"
          }
        ],
        "mbid": "",
        "album": {
          "mbid": "",
          "#text": "Cozy - Single"
        },
        "name": "Cozy",
        "url": "https://www.last.fm/music/Jeremy+Zucker,+Lauv+&+Alexander+23/_/Cozy",
        "date": {
          "uts": "1716568270",
          "#text": "24 May 2024, 16:31"
        }
      },
      {
        "artist": {
          "mbid": "c0ef2ba5-a7b7-40ea-bd27-30acccfcac11",
          "#text": "Lauv"
        },
        "streamable": "0",
        "image": [
          {
            "size": "small",
            "#text": "https://lastfm.freetls.fastly.net/i/u/34s/fff716db0b935ab873c03e7b95fca9e3.jpg"
          },
          {
            "size": "medium",
            "#text": "https://lastfm.freetls.fastly.net/i/u/64s/fff716db0b935ab873c03e7b95fca9e3.jpg"
          },
          {
            "size": "large",
            "#text": "https://lastfm.freetls.fastly.net/i/u/174s/fff716db0b935ab873c03e7b95fca9e3.jpg"
          },
          {
            "size": "extralarge",
            "#text": "https://lastfm.freetls.fastly.net/i/u/300x300/fff716db0b935ab873c03e7b95fca9e3.jpg"
          }
        ],
        "mbid": "4fbb1e4a-c5c7-4694-a971-a3668bcffa17",
        "album": {
          "mbid": "10540bc4-38c8-498d-83e3-5c7b23a5245e",
          "#text": "~how i'm feeling~"
        },
        "name": "Feelings",
        "url": "https://www.last.fm/music/Lauv/_/Feelings",
        "date": {
          "uts": "1716549644",
          "#text": "24 May 2024, 11:20"
        }
      },
      {
        "artist": {
          "mbid": "b8a7c51f-362c-4dcb-a259-bc6e0095f0a6",
          "#text": "Ed Sheeran"
        },
        "streamable": "0",
        "image": [
          {
            "size": "small",
            "#text": "https://lastfm.freetls.fastly.net/i/u/34s/355b0e1174e7c72669cf82f2382115e2.jpg"
          },
          {
            "size": "medium",
            "#text": "https://lastfm.freetls.fastly.net/i/u/64s/355b0e1174e7c72669cf82f2382115e2.jpg"
          },
          {
            "size": "large",
            "#text": "https://lastfm.freetls.fastly.net/i/u/174s/355b0e1174e7c72669cf82f2382115e2.jpg"
          },
          {
            "size": "extralarge",
            "#text": "https://lastfm.freetls.fastly.net/i/u/300x300/355b0e1174e7c72669cf82f2382115e2.jpg"
          }
        ],
        "mbid": "cb2cc207-8125-445c-9ef9-6ea44eee959a",
        "album": {
          "mbid": "3ec0cc3a-d3ff-4dff-8509-a133637debca",
          "#text": "x (Deluxe Edition)"
        },
        "name": "Thinking Out Loud",
        "url": "https://www.last.fm/music/Ed+Sheeran/_/Thinking+Out+Loud",
        "date": {
          "uts": "1716549357",
          "#text": "24 May 2024, 11:15"
        }
      },
      {
        "artist": {
          "mbid": "f1cc066a-6dd1-4b18-ae68-3708472ab4b1",
          "#text": "Lany"
        },
        "streamable": "0",
        "image": [
          {
            "size": "small",
            "#text": "https://lastfm.freetls.fastly.net/i/u/34s/b6c33ae7215181697acfb8fde7780b20.jpg"
          },
          {
            "size": "medium",
            "#text": "https://lastfm.freetls.fastly.net/i/u/64s/b6c33ae7215181697acfb8fde7780b20.jpg"
          },
          {
            "size": "large",
            "#text": "https://lastfm.freetls.fastly.net/i/u/174s/b6c33ae7215181697acfb8fde7780b20.jpg"
          },
          {
            "size": "extralarge",
            "#text": "https://lastfm.freetls.fastly.net/i/u/300x300/b6c33ae7215181697acfb8fde7780b20.jpg"
          }
        ],
        "mbid": "02c44f63-031e-4937-a405-b302d588cf83",
        "album": {
          "mbid": "184d08b5-1e0e-45ba-9dd1-ff2a912c4dfb",
          "#text": "gg bb xx (deluxe)"
        },
        "name": "dna",
        "url": "https://www.last.fm/music/Lany/_/dna",
        "date": {
          "uts": "1716549127",
          "#text": "24 May 2024, 11:12"
        }
      },
      {
        "artist": {
          "mbid": "b8a7c51f-362c-4dcb-a259-bc6e0095f0a6",
          "#text": "Ed Sheeran"
        },
        "streamable": "0",
        "image": [
          {
            "size": "small",
            "#text": "https://lastfm.freetls.fastly.net/i/u/34s/132e30ae83472d37194f45427be248b7.jpg"
          },
          {
            "size": "medium",
            "#text": "https://lastfm.freetls.fastly.net/i/u/64s/132e30ae83472d37194f45427be248b7.jpg"
          },
          {
            "size": "large",
            "#text": "https://lastfm.freetls.fastly.net/i/u/174s/132e30ae83472d37194f45427be248b7.jpg"
          },
          {
            "size": "extralarge",
            "#text": "https://lastfm.freetls.fastly.net/i/u/300x300/132e30ae83472d37194f45427be248b7.jpg"
          }
        ],
        "mbid": "dbc2d8c2-2028-4401-b7da-5b55f2bb696b",
        "album": {
          "mbid": "6d7524b5-b862-42e2-8661-4130ff6f1002",
          "#text": "- (Deluxe)"
        },
        "name": "Eyes Closed",
        "url": "https://www.last.fm/music/Ed+Sheeran/_/Eyes+Closed",
        "date": {
          "uts": "1716548942",
          "#text": "24 May 2024, 11:09"
        }
      },
      {
        "artist": {
          "mbid": "28737730-ec70-4da5-89c5-77ac13c5c34d",
          "#text": "Khalid"
        },
        "streamable": "0",
        "image": [
          {
            "size": "small",
            "#text": "https://lastfm.freetls.fastly.net/i/u/34s/20536b4149df70b97dca0e6374a608a3.jpg"
          },
          {
            "size": "medium",
            "#text": "https://lastfm.freetls.fastly.net/i/u/64s/20536b4149df70b97dca0e6374a608a3.jpg"
          },
          {
            "size": "large",
            "#text": "https://lastfm.freetls.fastly.net/i/u/174s/20536b4149df70b97dca0e6374a608a3.jpg"
          },
          {
            "size": "extralarge",
            "#text": "https://lastfm.freetls.fastly.net/i/u/300x300/20536b4149df70b97dca0e6374a608a3.jpg"
          }
        ],
        "mbid": "",
        "album": {
          "mbid": "3a5cbae4-5b58-4428-b278-47d0157f200d",
          "#text": "Free Spirit"
        },
        "name": "Talk (feat. Disclosure)",
        "url": "https://www.last.fm/music/Khalid/_/Talk+(feat.+Disclosure)",
        "date": {
          "uts": "1716548745",
          "#text": "24 May 2024, 11:05"
        }
      },
      {
        "artist": {
          "mbid": "c8b03190-306c-4120-bb0b-6f2ebfc06ea9",
          "#text": "The Weeknd"
        },
        "streamable": "0",
        "image": [
          {
            "size": "small",
            "#text": "https://lastfm.freetls.fastly.net/i/u/34s/7d957bd27dd562bee7aaa89eafa0bbe6.jpg"
          },
          {
            "size": "medium",
            "#text": "https://lastfm.freetls.fastly.net/i/u/64s/7d957bd27dd562bee7aaa89eafa0bbe6.jpg"
          },
          {
            "size": "large",
            "#text": "https://lastfm.freetls.fastly.net/i/u/174s/7d957bd27dd562bee7aaa89eafa0bbe6.jpg"
          },
          {
            "size": "extralarge",
            "#text": "https://lastfm.freetls.fastly.net/i/u/300x300/7d957bd27dd562bee7aaa89eafa0bbe6.jpg"
          }
        ],
        "mbid": "",
        "album": {
          "mbid": "8a61af61-cb44-497e-9bb1-2b7b137b3bfe",
          "#text": "After Hours"
        },
        "name": "Blinding Lights",
        "url": "https://www.last.fm/music/The+Weeknd/_/Blinding+Lights",
        "date": {
          "uts": "1716548547",
          "#text": "24 May 2024, 11:02"
        }
      },
      {
        "artist": {
          "mbid": "6e91d65a-ab21-49b7-b81d-11c53c65601a",
          "#text": "Valley"
        },
        "streamable": "0",
        "image": [
          {
            "size": "small",
            "#text": "https://lastfm.freetls.fastly.net/i/u/34s/102eb123822c1d986641a5580e0632cf.jpg"
          },
          {
            "size": "medium",
            "#text": "https://lastfm.freetls.fastly.net/i/u/64s/102eb123822c1d986641a5580e0632cf.jpg"
          },
          {
            "size": "large",
            "#text": "https://lastfm.freetls.fastly.net/i/u/174s/102eb123822c1d986641a5580e0632cf.jpg"
          },
          {
            "size": "extralarge",
            "#text": "https://lastfm.freetls.fastly.net/i/u/300x300/102eb123822c1d986641a5580e0632cf.jpg"
          }
        ],
        "mbid": "533cbf5f-483a-41f0-9d5e-604c1ffbed67",
        "album": {
          "mbid": "",
          "#text": "sucks to see you doing better (extended)"
        },
        "name": "homebody",
        "url": "https://www.last.fm/music/Valley/_/homebody",
        "date": {
          "uts": "1716548351",
          "#text": "24 May 2024, 10:59"
        }
      },
      {
        "artist": {
          "mbid": "525f1f1c-03f0-4bc8-8dfd-e7521f87631b",
          "#text": "Charlie Puth"
        },
        "streamable": "0",
        "image": [
          {
            "size": "small",
            "#text": "https://lastfm.freetls.fastly.net/i/u/34s/1f4d106bfc5a4d0e8dcec8490630fab3.jpg"
          },
          {
            "size": "medium",
            "#text": "https://lastfm.freetls.fastly.net/i/u/64s/1f4d106bfc5a4d0e8dcec8490630fab3.jpg"
          },
          {
            "size": "large",
            "#text": "https://lastfm.freetls.fastly.net/i/u/174s/1f4d106bfc5a4d0e8dcec8490630fab3.jpg"
          },
          {
            "size": "extralarge",
            "#text": "https://lastfm.freetls.fastly.net/i/u/300x300/1f4d106bfc5a4d0e8dcec8490630fab3.jpg"
          }
        ],
        "mbid": "a8bdddfe-aafa-46bb-9c68-6ec54f8e9eb4",
        "album": {
          "mbid": "f1df0b2e-d00c-4686-810d-1f633ecb4aee",
          "#text": "CHARLIE"
        },
        "name": "Smells Like Me",
        "url": "https://www.last.fm/music/Charlie+Puth/_/Smells+Like+Me",
        "date": {
          "uts": "1716548153",
          "#text": "24 May 2024, 10:55"
        }
      },
      {
        "artist": {
          "mbid": "c0ef2ba5-a7b7-40ea-bd27-30acccfcac11",
          "#text": "Lauv & Troye Sivan"
        },
        "streamable": "0",
        "image": [
          {
            "size": "small",
            "#text": "https://lastfm.freetls.fastly.net/i/u/34s/36a8423e9c86db2d5d712110fe78b7b0.jpg"
          },
          {
            "size": "medium",
            "#text": "https://lastfm.freetls.fastly.net/i/u/64s/36a8423e9c86db2d5d712110fe78b7b0.jpg"
          },
          {
            "size": "large",
            "#text": "https://lastfm.freetls.fastly.net/i/u/174s/36a8423e9c86db2d5d712110fe78b7b0.jpg"
          },
          {
            "size": "extralarge",
            "#text": "https://lastfm.freetls.fastly.net/i/u/300x300/36a8423e9c86db2d5d712110fe78b7b0.jpg"
          }
        ],
        "mbid": "0bbcf5c2-a2ca-435f-944d-f4c767a0432d",
        "album": {
          "mbid": "",
          "#text": "i'm so tired... - Single"
        },
        "name": "i'm so tired...",
        "url": "https://www.last.fm/music/Lauv+&+Troye+Sivan/_/i%27m+so+tired...",
        "date": {
          "uts": "1716547970",
          "#text": "24 May 2024, 10:52"
        }
      },
      {
        "artist": {
          "mbid": "b1e26560-60e5-4236-bbdb-9aa5a8d5ee19",
          "#text": "Post Malone"
        },
        "streamable": "0",
        "image": [
          {
            "size": "small",
            "#text": "https://lastfm.freetls.fastly.net/i/u/34s/53f65efa74120514ef6c94d1fa30580d.jpg"
          },
          {
            "size": "medium",
            "#text": "https://lastfm.freetls.fastly.net/i/u/64s/53f65efa74120514ef6c94d1fa30580d.jpg"
          },
          {
            "size": "large",
            "#text": "https://lastfm.freetls.fastly.net/i/u/174s/53f65efa74120514ef6c94d1fa30580d.jpg"
          },
          {
            "size": "extralarge",
            "#text": "https://lastfm.freetls.fastly.net/i/u/300x300/53f65efa74120514ef6c94d1fa30580d.jpg"
          }
        ],
        "mbid": "9d0a9e5c-a765-40ab-837e-99b0bb197f6c",
        "album": {
          "mbid": "0b751b1b-f420-46e9-b2b5-108615b8427f",
          "#text": "Hollywood's Bleeding"
        },
        "name": "Circles",
        "url": "https://www.last.fm/music/Post+Malone/_/Circles",
        "date": {
          "uts": "1716547780",
          "#text": "24 May 2024, 10:49"
        }
      },
      {
        "artist": {
          "mbid": "b7d92248-97e3-4450-8057-6fe06738f735",
          "#text": "Shawn Mendes"
        },
        "streamable": "0",
        "image": [
          {
            "size": "small",
            "#text": "https://lastfm.freetls.fastly.net/i/u/34s/87de33650984273a54786a0fe33fefb4.png"
          },
          {
            "size": "medium",
            "#text": "https://lastfm.freetls.fastly.net/i/u/64s/87de33650984273a54786a0fe33fefb4.png"
          },
          {
            "size": "large",
            "#text": "https://lastfm.freetls.fastly.net/i/u/174s/87de33650984273a54786a0fe33fefb4.png"
          },
          {
            "size": "extralarge",
            "#text": "https://lastfm.freetls.fastly.net/i/u/300x300/87de33650984273a54786a0fe33fefb4.png"
          }
        ],
        "mbid": "",
        "album": {
          "mbid": "",
          "#text": "If I Can't Have You - Single"
        },
        "name": "If I Can't Have You",
        "url": "https://www.last.fm/music/Shawn+Mendes/_/If+I+Can%27t+Have+You",
        "date": {
          "uts": "1716547574",
          "#text": "24 May 2024, 10:46"
        }
      }
    ],
    "@attr": {
      "user": "injoon5",
      "totalPages": "100",
      "page": "1",
      "perPage": "50",
      "total": "4972"
    }
  }
}