{
  "recenttracks": {
    "track": [
      {
        "artist": {
          "mbid": "",
          "#text": "Yoo Jae Ha"
        },
        "streamable": "0",
        "image": [
          {
            "size": "small",
            "#text": "https://lastfm.freetls.fastly.net/i/u/34s/2a96cbd8b46e442fc41c2b86b821562f.png"
          },
          {
            "size": "medium",
            "#text": "https://lastfm.freetls.fastly.net/i/u/64s/2a96cbd8b46e442fc41c2b86b821562f.png"
          },
          {
            "size": "large",
            "#text": "https://lastfm.freetls.fastly.net/i/u/174s/2a96cbd8b46e442fc41c2b86b821562f.png"
          },
          {
            "size": "extralarge",
            "#text": "https://lastfm.freetls.fastly.net/i/u/300x300/2a96cbd8b46e442fc41c2b86b821562f.png"
          }
        ],
        "mbid": "",
        "album": {
          "mbid": "",
          "#text": "\uc0ac\ub791\ud558\uae30 \ub54c\ubb38\uc5d0 (Remastering Version)"
        },
        "name": "\ub0b4 \ub9c8\uc74c\uc5d0 \ube44\uce5c \ub0b4 \ubaa8\uc2b5",
        "@attr": {
          "nowplaying": "true"
        },
        "url": "https://www.last.fm/music/Yoo+Jae+Ha/_/%EB%82%B4+%EB%A7%88%EC%9D%8C%EC%97%90+%EB%B9%84%EC%B9%9C+%EB%82%B4+%EB%AA%A8%EC%8A%B5"
      },
      {
        "artist": {
          "mbid": "",
          "#text": "Yoo Jae Ha"
        },
        "streamable": "0",
        "image": [
          {
            "size": "small",
            "#text": "https://lastfm.freetls.fastly.net/i/u/34s/2a96cbd8b46e442fc41c2b86b821562f.png"
          },
          {
            "size": "medium",
            "#text": "https://lastfm.freetls.fastly.net/i/u/64s/2a96cbd8b46e442fc41c2b86b821562f.png"
          },
          {
            "size": "large",
            "#text": "https://lastfm.freetls.fastly.net/i/u/174s/2a96cbd8b46e442fc41c2b86b821562f.png"
          },
          {
            "size": "extralarge",
            "#text": "https://lastfm.freetls.fastly.net/i/u/300x300/2a96cbd8b46e442fc41c2b86b821562f.png"
          }
        ],
        "mbid": "",
        "album": {
          "mbid": "",
          "#text": "\uc0ac\ub791\ud558\uae30 \ub54c\ubb38\uc5d0 (Remastering Version)"
        },
        "name": "\ub0b4 \ub9c8\uc74c\uc5d0 \ube44\uce5c \ub0b4 \ubaa8\uc2b5",
        "url": "https://www.last.fm/music/Yoo+Jae+Ha/_/%EB%82%B4+%EB%A7%88%EC%9D%8C%EC%97%90+%EB%B9%84%EC%B9%9C+%EB%82%B4+%EB%AA%A8%EC%8A%B5",
        "date": {
          "uts": "1765118608",
          "#text": "07 Dec 2025, 14:43"
        }
      },
      {
        "artist": {
          "mbid": "a74b1b7f-71a5-4011-9441-d0b5e4122711",
          "#text": "Radiohead"
        },
        "streamable": "0",
        "image": [
          {
            "size": "small",
            "#text": "https://lastfm.freetls.fastly.net/i/u/34s/9ea9931e129bb5efd3606866901855b5.jpg"
          },
          {
            "size": "medium",
            "#text": "https://lastfm.freetls.fastly.net/i/u/64s/9ea9931e129bb5efd3606866901855b5.jpg"
          },
          {
            "size": "large",
            "#text": "https://lastfm.freetls.fastly.net/i/u/174s/9ea9931e129bb5efd3606866901855b5.jpg"
          },
          {
            "size": "extralarge",
            "#text": "https://lastfm.freetls.fastly.net/i/u/300x300/9ea9931e129bb5efd3606866901855b5.jpg"
          }
        ],
        "mbid": "",
        "album": {
          "mbid": "0405cb4c-fc88-3338-b5d6-1fa71a9562e4",
          "#text": "The Bends"
        },
        "name": "High and Dry",
        "url": "https://www.last.fm/music/Radiohead/_/High+and+Dry",
        "date": {
          "uts": "1765116392",
          "#text": "07 Dec 2025, 14:06"
        }
      },
      {
        "artist": {
          "mbid": "",
          "#text": "Yoo Jae Ha"
        },
        "streamable": "0",
        "image": [
          {
            "size": "small",
            "#text": "https://lastfm.freetls.fastly.net/i/u/34s/2a96cbd8b46e442fc41c2b86b821562f.png"
          },
          {
            "size": "medium",
            "#text": "https://lastfm.freetls.fastly.net/i/u/64s/2a96cbd8b46e442fc41c2b86b821562f.png"
          },
          {
            "size": "large",
            "#text": "https://lastfm.freetls.fastly.net/i/u/174s/2a96cbd8b46e442fc41c2b86b821562f.png"
          },
          {
            "size": "extralarge",
            "#text": "https://lastfm.freetls.fastly.net/i/u/300x300/2a96cbd8b46e442fc41c2b86b821562f.png"
          }
        ],
        "mbid": "",
        "album": {
          "mbid": "",
          "#text": "\uc0ac\ub791\ud558\uae30 \ub54c\ubb38\uc5d0 (Remastering Version)"
        },
        "name": "\ub0b4 \ub9c8\uc74c\uc5d0 \ube44\uce5c \ub0b4 \ubaa8\uc2b5",
        "url": "https://www.last.fm/music/Yoo+Jae+Ha/_/%EB%82%B4+%EB%A7%88%EC%9D%8C%EC%97%90+%EB%B9%84%EC%B9%9C+%EB%82%B4+%EB%AA%A8%EC%8A%B5",
        "date": {
          "uts": "1765116229",
          "#text": "07 Dec 2025, 14:03"
        }
      }
    ],
    "@attr": {
      "user": "injoon5",
      "totalPages": "159",
      "page": "1",
      "perPage": "50",
      "total": "7935"
    }
  }
}