{
  "recenttracks": {
    "track": [
      {
        "artist": {
          "mbid": "",
          "#text": "slchld"
        },
        "streamable": "0",
        "image": [
          {
            "size": "small",
            "#text": "https://lastfm.freetls.fastly.net/i/u/34s/2a96cbd8b46e442fc41c2b86b821562f.png"
          },
          {
            "size": "medium",
            "#text": "https://lastfm.freetls.fastly.net/i/u/64s/2a96cbd8b46e442fc41c2b86b821562f.png"
          },
          {
            "size": "large",
            "#text": "https://lastfm.freetls.fastly.net/i/u/174s/2a96cbd8b46e442fc41c2b86b821562f.png"
          },
          {
            "size": "extralarge",
            "#text": "https://lastfm.freetls.fastly.net/i/u/300x300/2a96cbd8b46e442fc41c2b86b821562f.png"
          }
        ],
        "mbid": "",
        "album": {
          "mbid": "",
          "#text": "You Won't Be There For Me - Single"
        },
        "name": "you won't be there for me",
        "@attr": {
          "nowplaying": "true"
        },
        "url": "https://www.last.fm/music/slchld/_/you+won%27t+be+there+for+me"
      },
      {
        "artist": {
          "mbid": "",
          "#text": "slchld"
        },
        "streamable": "0",
        "image": [
          {
            "size": "small",
            "#text": "https://lastfm.freetls.fastly.net/i/u/34s/2a96cbd8b46e442fc41c2b86b821562f.png"
          },
          {
            "size": "medium",
            "#text": "https://lastfm.freetls.fastly.net/i/u/64s/2a96cbd8b46e442fc41c2b86b821562f.png"
          },
          {
            "size": "large",
            "#text": "https://lastfm.freetls.fastly.net/i/u/174s/2a96cbd8b46e442fc41c2b86b821562f.png"
          },
          {
            "size": "extralarge",
            "#text": "https://lastfm.freetls.fastly.net/i/u/300x300/2a96cbd8b46e442fc41c2b86b821562f.png"
          }
        ],
        "mbid": "43af4346-c2a1-4a60-91df-7b8b4a6e97ab",
        "album": {
          "mbid": "",
          "#text": "My Insecurities, Not Yours - EP"
        },
        "name": "she likes spring, I prefer winter",
        "url": "https://www.last.fm/music/slchld/_/she+likes+spring,+I+prefer+winter",
        "date": {
          "uts": "1729356670",
          "#text": "19 Oct 2024, 16:51"
        }
      },
      {
        "artist": {
          "mbid": "",
          "#text": "slchld"
        },
        "streamable": "0",
        "image": [
          {
            "size": "small",
            "#text": "https://lastfm.freetls.fastly.net/i/u/34s/92dc4ed6d30d9aad0eee1a74224e0f9b.jpg"
          },
          {
            "size": "medium",
            "#text": "https://lastfm.freetls.fastly.net/i/u/64s/92dc4ed6d30d9aad0eee1a74224e0f9b.jpg"
          },
          {
            "size": "large",
            "#text": "https://lastfm.freetls.fastly.net/i/u/174s/92dc4ed6d30d9aad0eee1a74224e0f9b.jpg"
          },
          {
            "size": "extralarge",
            "#text": "https://lastfm.freetls.fastly.net/i/u/300x300/92dc4ed6d30d9aad0eee1a74224e0f9b.jpg"
          }
        ],
        "mbid": "",
        "album": {
          "mbid": "",
          "#text": "camellia - Single"
        },
        "name": "camellia",
        "url": "https://www.last.fm/music/slchld/_/camellia",
        "date": {
          "uts": "1729356490",
          "#text": "19 Oct 2024, 16:48"
        }
      },
      {
        "artist": {
          "mbid": "0dc80325-33bf-4120-9cc6-ca6caae39571",
          "#text": "mellow fellow"
        },
        "streamable": "0",
        "image": [
          {
            "size": "small",
            "#text": "https://lastfm.freetls.fastly.net/i/u/34s/25d83c00a9b3076dd29727b9528e8428.jpg"
          },
          {
            "size": "medium",
            "#text": "https://lastfm.freetls.fastly.net/i/u/64s/25d83c00a9b3076dd29727b9528e8428.jpg"
          },
          {
            "size": "large",
            "#text": "https://lastfm.freetls.fastly.net/i/u/174s/25d83c00a9b3076dd29727b9528e8428.jpg"
          },
          {
            "size": "extralarge",
            "#text": "https://lastfm.freetls.fastly.net/i/u/300x300/25d83c00a9b3076dd29727b9528e8428.jpg"
          }
        ],
        "mbid": "1e6e27cd-f927-4fb2-a61a-89903328cd51",
        "album": {
          "mbid": "",
          "#text": "Dancing - Single"
        },
        "name": "dancing",
        "url": "https://www.last.fm/music/mellow+fellow/_/dancing",
        "date": {
          "uts": "1729356261",
          "#text": "19 Oct 2024, 16:44"
        }
      }
    ],
    "@attr": {
      "user": "injoon5",
      "totalPages": "114",
      "page": "1",
      "perPage": "50",
      "total": "5653"
    }
  }
}